src/ex0.sv
`timescale 1ns/1ps

module ex0 (
    input logic a, b,
    output logic c
);

    assign c = a | b;       //OR
endmodule

module tb_ex0 ();

    logic tb_a, tb_b, tb_c;

    ex0 dut (
        .a(tb_a),
        .b(tb_b),
        .c(tb_c)
    );      

    initial begin
        $dumpfile("ex0.vcd");       //don't include for vivado
        $dumpvars(0, tb_ex0);       //don't include for vivado
        tb_a = 0;
        tb_b = 0;
    end

    always begin
        #5 tb_a = ~tb_a;
    end

    always begin
        #10 tb_b = ~tb_b;
    end

    always begin
        #100;
        $finish;
    end
endmodule

src/Oct_5/ex0.vcd
$date
	Mon Oct  5 20:17:57 2026
$end
$version
	Icarus Verilog
$end
$timescale
	1ps
$end
$scope module tb_ex0 $end
$var wire 1 ! tb_c $end
$var reg 1 " tb_a $end
$var reg 1 # tb_b $end
$scope module dut $end
$var wire 1 " a $end
$var wire 1 # b $end
$var wire 1 ! c $end
$upscope $end
$upscope $end
$enddefinitions $end
$comment Show the parameter values. $end
$dumpall
$end
#0
$dumpvars
0#
0"
0!
$end
#5000
1!
1"
#10000
0"
1#
#15000
1"
#20000
0!
0"
0#
#25000
1!
1"
#30000
0"
1#
#35000
1"
#40000
0!
0"
0#
#45000
1!
1"
#50000
0"
1#
#55000
1"
#60000
0!
0"
0#
#65000
1!
1"
#70000
0"
1#
#75000
1"
#80000
0!
0"
0#
#85000
1!
1"
#90000
0"
1#
#95000
1"
#100000
0!
0"
0#
